russianLosses/__init__.py
russianLosses-4.5.dist-info/METADATA
russianLosses-4.5.dist-info/WHEEL
russianLosses-4.5.dist-info/top_level.txt
russianLosses-4.5.dist-info/RECORD
