Metadata-Version: 2.1
Name: russianLosses
Version: 4.5
Summary: The module provides data on Russias losses in the war with Ukraine
Author: nazarrudenok
Author-email: rudenokpy@gmail.com
Classifier: Programming Language :: Python :: 3
Classifier: License :: OSI Approved :: MIT License
Classifier: Operating System :: OS Independent
Requires-Python: >=3.6
